secret_updater/__init__.py
secret_updater/main.py
secret_updater/secret-updater.py
secret_updater-0.1.2.dist-info/LICENCE
secret_updater-0.1.2.dist-info/METADATA
secret_updater-0.1.2.dist-info/WHEEL
secret_updater-0.1.2.dist-info/entry_points.txt
secret_updater-0.1.2.dist-info/top_level.txt
secret_updater-0.1.2.dist-info/RECORD
