Metadata-Version: 2.1
Name: secret-updater
Version: 0.1.2
Summary: CLI tool to update GitHub repository secrets.
Home-page: https://github.com/scribe-security/secret-updater
Author: Daniel Nebenzahl
Author-email: dn@scribesecurity.com
Classifier: Programming Language :: Python :: 3
Classifier: License :: OSI Approved :: MIT License
Classifier: Operating System :: OS Independent
Requires-Python: >=3.6
License-File: LICENCE
Requires-Dist: pynacl
Requires-Dist: requests
